py_github_helper/__init__.py
py_github_helper/__main__.py
py_github_helper/utils/__init__.py
py_github_helper/utils/commands.py
py_github_helper/utils/custom_arg_parser.py
py_github_helper/utils/util.py
py_github_helper-0.2.6.dist-info/licenses/LICENSE
py_github_helper-0.2.6.dist-info/METADATA
py_github_helper-0.2.6.dist-info/WHEEL
py_github_helper-0.2.6.dist-info/top_level.txt
py_github_helper-0.2.6.dist-info/RECORD
