Metadata-Version: 2.4
Name: py_github_helper
Version: 0.2.6
Summary: Python Script for interacting with Github API
Home-page: https://github.com/org-not-included/py-github-helper/
Author: mtsadler (Mike Sadler)
Author-email: <michaeltsadler1@gmail.com>
Keywords: python,github,api,comment,action,Pull Request
Classifier: Intended Audience :: Developers
Classifier: Programming Language :: Python :: 3
Classifier: Operating System :: Unix
Classifier: Operating System :: MacOS :: MacOS X
Classifier: Operating System :: Microsoft :: Windows
License-File: LICENSE
Requires-Dist: requests
Requires-Dist: pendulum
Dynamic: author
Dynamic: author-email
Dynamic: classifier
Dynamic: description
Dynamic: description-content-type
Dynamic: home-page
Dynamic: keywords
Dynamic: license-file
Dynamic: requires-dist
Dynamic: summary
